idb_mcp/__init__.py
idb_mcp/__main__.py
idb_mcp/idb/__init__.py
idb_mcp/idb/idb_controller.py
idb_mcp/idb/idb_error.py
idb_mcp/idb/idb_wrapper.py
idb_mcp/idb/ios_device.py
idb_mcp/idb/ios_device_collection.py
idb_mcp/mcp/__init__.py
idb_mcp/mcp/server.py
idb_mcp/utils/__init__.py
idb_mcp/utils/image_utils.py
idb_mcp-0.1.0.dist-info/licenses/LICENSE
idb_mcp-0.1.0.dist-info/METADATA
idb_mcp-0.1.0.dist-info/WHEEL
idb_mcp-0.1.0.dist-info/entry_points.txt
idb_mcp-0.1.0.dist-info/top_level.txt
idb_mcp-0.1.0.dist-info/RECORD
