Metadata-Version: 2.4
Name: idb-mcp
Version: 0.1.0
Summary: An MCP server and importable Python module that wraps Facebook IDB to control iOS simulators for automation. Implemented by AskUI.
Author: askui GmbH
Author-email: info@askui.com
License: MIT
Project-URL: Homepage, https://github.com/askui/idb-mcp
Classifier: Programming Language :: Python :: 3
Classifier: License :: OSI Approved :: MIT License
Classifier: Operating System :: MacOS :: MacOS X
Requires-Python: >=3.10
License-File: LICENSE
Requires-Dist: fb-idb==1.1.7
Requires-Dist: pillow==11.3.0
Requires-Dist: fastmcp==2.12.3
Dynamic: license-file
